chatllama/__init__.py
chatllama/llama_model.py
chatllama/__pycache__/__init__.cpython-38.pyc
chatllama/langchain_modules/__init__.py
chatllama/langchain_modules/prompt_templates.py
chatllama/langchain_modules/__pycache__/__init__.cpython-38.pyc
chatllama/langchain_modules/__pycache__/prompt_templates.cpython-38.pyc
chatllama/rlhf/__init__.py
chatllama/rlhf/actor.py
chatllama/rlhf/config.py
chatllama/rlhf/config.yaml
chatllama/rlhf/reward.py
chatllama/rlhf/test.py
chatllama/rlhf/trainer.py
chatllama/rlhf/utils.py
chatllama/rlhf/__pycache__/__init__.cpython-38.pyc
chatllama/rlhf/__pycache__/actor.cpython-38.pyc
chatllama/rlhf/__pycache__/config.cpython-38.pyc
chatllama/rlhf/__pycache__/reward.cpython-38.pyc
chatllama/rlhf/__pycache__/test.cpython-38.pyc
chatllama/rlhf/__pycache__/trainer.cpython-38.pyc
chatllama/rlhf/__pycache__/utils.cpython-38.pyc
chatllama-0.0.4.dist-info/METADATA
chatllama-0.0.4.dist-info/WHEEL
chatllama-0.0.4.dist-info/top_level.txt
chatllama-0.0.4.dist-info/RECORD
