Metadata-Version: 2.1
Name: chatllama
Version: 0.0.4
Summary: ChatLLaMA: Open and Efficient Foundation Language Models Runnable In A Single GPU
Home-page: https://github.com/juncongmoo/chatllama
Author-email: <juncongmoo@gmail.com>
License: UNKNOWN
Keywords: ChatLLaMA,LLaMA
Platform: UNKNOWN
Classifier: Development Status :: 3 - Alpha
Classifier: Programming Language :: Python :: 3
Classifier: Programming Language :: Python :: 3.8
Classifier: Programming Language :: Python :: 3.9
Classifier: Programming Language :: Python :: 3.10
Requires-Dist: pyllama
Requires-Dist: fairscale
Requires-Dist: langchain
Requires-Dist: beartype
Requires-Dist: einops
Requires-Dist: plotly
